Workbook

Sheet Inputs
A1: BTC-Backed Loan Model v2 Inputs
A3: Input | B3: Value | C3: Unit | D3: Notes
A4: Shared
A5: Current BTC Price | B5: 60000 | C5: USD | D5: Year 0 price; feeds Price Projection
A6: Annual BTC Price Growth | B6: 0 | C6: % | D6: Editable flat/default projection growth rate
A7: Starting BTC | B7: 2 | C7: BTC | D7: Collateral used by both engines
A8: Borrow APR | B8: 0.1 | C8: % | D8: Interest accrues on start-of-row debt
A9: Interest Treatment | B9: capitalized | C9: choice | D9: capitalized or paid externally
A10: Margin Call LTV | B10: 0.7 | C10: % | D10: Risk threshold
A11: Liquidation LTV | B11: 0.75 | C11: % | D11: Risk threshold
A12: Minimum Liquidation Buffer | B12: 0.5 | C12: % | D12: Required price-drop buffer
A13: Accumulation
A14: Target Effective LTV | B14: 0.25 | C14: % | D14: Recursive setup/top-up target
A15: Max Effective LTV | B15: 0.35 | C15: % | D15: Hard cap
A16: Setup Collateral BTC | B16: 2.6666667 | C16: BTC | D16: Computed audit output
A17: Income
A18: Max Available Annual Income (Year 1) | B18: 42000 | C18: USD | D18: Calculated from BTC collateral, LTV ceiling, and liquidation buffer
A19: Selected Annual Income Draw | B19: 50000 | C19: USD | D19: User-selected draw; capped by max available annual income
A20: Income LTV Ceiling | B20: 0.35 | C20: % | D20: Safe debt ceiling
A21: Setup Collateral BTC | B21: 2 | C21: BTC | D21: Income keeps BTC constant

Sheet Price Projection
A1: Price Projection
A3: Year | B3: BTC Price | C3: Scenario | D3: YoY Change
A4: 0 | B4: ='Inputs'!$B$5 | C4: Editable formula projection | D4: 0
A5: 1 | B5: =B4*(1+'Inputs'!$B$6) | C5: Editable formula projection | D5: =B5/B4-1
A6: 2 | B6: =B5*(1+'Inputs'!$B$6) | C6: Editable formula projection | D6: =B6/B5-1
A7: 3 | B7: =B6*(1+'Inputs'!$B$6) | C7: Editable formula projection | D7: =B7/B6-1
A8: 4 | B8: =B7*(1+'Inputs'!$B$6) | C8: Editable formula projection | D8: =B8/B7-1
A9: 5 | B9: =B8*(1+'Inputs'!$B$6) | C9: Editable formula projection | D9: =B9/B8-1
A10: 6 | B10: =B9*(1+'Inputs'!$B$6) | C10: Editable formula projection | D10: =B10/B9-1
A11: 7 | B11: =B10*(1+'Inputs'!$B$6) | C11: Editable formula projection | D11: =B11/B10-1
A12: 8 | B12: =B11*(1+'Inputs'!$B$6) | C12: Editable formula projection | D12: =B12/B11-1
A13: 9 | B13: =B12*(1+'Inputs'!$B$6) | C13: Editable formula projection | D13: =B13/B12-1
A14: 10 | B14: =B13*(1+'Inputs'!$B$6) | C14: Editable formula projection | D14: =B14/B13-1

Sheet Accumulation Engine
A1: Accumulation Engine — Recursive BTC Leverage
A3: Year | B3: BTC Price | C3: Starting Collateral BTC | D3: Starting Debt | E3: Interest Accrued | F3: Debt After Interest | G3: Pre-Action LTV | H3: New Borrowing | I3: BTC Bought | J3: Ending Collateral BTC | K3: Ending Debt | L3: Gross BTC Held | M3: Debt BTC Equivalent | N3: Net BTC After Debt | O3: Extra BTC vs Passive | P3: Net Equity USD | Q3: Effective LTV End | R3: Leverage Multiple | S3: Margin-Call Price | T3: Liquidation Price | U3: Drop to Liquidation | V3: Risk Status
A4: 0 | B4: ='Price Projection'!B4 | C4: 2 | D4: 0 | E4: 0 | F4: 0 | G4: 0 | H4: 40000 | I4: 0.66666667 | J4: 2.6666667 | K4: 40000 | L4: 2.6666667 | M4: 0.66666667 | N4: 2 | O4: 0.66666667 | P4: 120000 | Q4: 0.25 | R4: 1.3333333 | S4: 21428.571 | T4: 20000 | U4: 0.66666667 | V4: SAFE
A5: 1 | B5: ='Price Projection'!B5 | C5: 2.6666667 | D5: 40000 | E5: 4000 | F5: 44000 | G5: 0.275 | H5: 0 | I5: 0 | J5: 2.6666667 | K5: 44000 | L5: 2.6666667 | M5: 0.73333333 | N5: 1.9333333 | O5: 0.66666667 | P5: 116000 | Q5: 0.275 | R5: 1.3333333 | S5: 23571.429 | T5: 22000 | U5: 0.63333333 | V5: SAFE
A6: 2 | B6: ='Price Projection'!B6 | C6: 2.6666667 | D6: 44000 | E6: 4400 | F6: 48400 | G6: 0.3025 | H6: 0 | I6: 0 | J6: 2.6666667 | K6: 48400 | L6: 2.6666667 | M6: 0.80666667 | N6: 1.86 | O6: 0.66666667 | P6: 111600 | Q6: 0.3025 | R6: 1.3333333 | S6: 25928.571 | T6: 24200 | U6: 0.59666667 | V6: SAFE
A7: 3 | B7: ='Price Projection'!B7 | C7: 2.6666667 | D7: 48400 | E7: 4840 | F7: 53240 | G7: 0.33275 | H7: 0 | I7: 0 | J7: 2.6666667 | K7: 53240 | L7: 2.6666667 | M7: 0.88733333 | N7: 1.7793333 | O7: 0.66666667 | P7: 106760 | Q7: 0.33275 | R7: 1.3333333 | S7: 28521.429 | T7: 26620 | U7: 0.55633333 | V7: SAFE
A8: 4 | B8: ='Price Projection'!B8 | C8: 2.6666667 | D8: 53240 | E8: 5324 | F8: 58564 | G8: 0.366025 | H8: 0 | I8: 0 | J8: 2.6666667 | K8: 58564 | L8: 2.6666667 | M8: 0.97606667 | N8: 1.6906 | O8: 0.66666667 | P8: 101436 | Q8: 0.366025 | R8: 1.3333333 | S8: 31373.571 | T8: 29282 | U8: 0.51196667 | V8: SAFE
A9: 5 | B9: ='Price Projection'!B9 | C9: 2.6666667 | D9: 58564 | E9: 5856.4 | F9: 64420.4 | G9: 0.4026275 | H9: 0 | I9: 0 | J9: 2.6666667 | K9: 64420.4 | L9: 2.6666667 | M9: 1.0736733 | N9: 1.5929933 | O9: 0.66666667 | P9: 95579.6 | Q9: 0.4026275 | R9: 1.3333333 | S9: 34510.929 | T9: 32210.2 | U9: 0.46316333 | V9: WARNING
A10: 6 | B10: ='Price Projection'!B10 | C10: 2.6666667 | D10: 64420.4 | E10: 6442.04 | F10: 70862.44 | G10: 0.44289025 | H10: 0 | I10: 0 | J10: 2.6666667 | K10: 70862.44 | L10: 2.6666667 | M10: 1.1810407 | N10: 1.485626 | O10: 0.66666667 | P10: 89137.56 | Q10: 0.44289025 | R10: 1.3333333 | S10: 37962.021 | T10: 35431.22 | U10: 0.40947967 | V10: WARNING
A11: 7 | B11: ='Price Projection'!B11 | C11: 2.6666667 | D11: 70862.44 | E11: 7086.244 | F11: 77948.684 | G11: 0.48717928 | H11: 0 | I11: 0 | J11: 2.6666667 | K11: 77948.684 | L11: 2.6666667 | M11: 1.2991447 | N11: 1.3675219 | O11: 0.66666667 | P11: 82051.316 | Q11: 0.48717928 | R11: 1.3333333 | S11: 41758.224 | T11: 38974.342 | U11: 0.35042763 | V11: WARNING
A12: 8 | B12: ='Price Projection'!B12 | C12: 2.6666667 | D12: 77948.684 | E12: 7794.8684 | F12: 85743.552 | G12: 0.5358972 | H12: 0 | I12: 0 | J12: 2.6666667 | K12: 85743.552 | L12: 2.6666667 | M12: 1.4290592 | N12: 1.2376075 | O12: 0.66666667 | P12: 74256.448 | Q12: 0.5358972 | R12: 1.3333333 | S12: 45934.046 | T12: 42871.776 | U12: 0.2854704 | V12: WARNING
A13: 9 | B13: ='Price Projection'!B13 | C13: 2.6666667 | D13: 85743.552 | E13: 8574.3552 | F13: 94317.908 | G13: 0.58948692 | H13: 0 | I13: 0 | J13: 2.6666667 | K13: 94317.908 | L13: 2.6666667 | M13: 1.5719651 | N13: 1.0947015 | O13: 0.66666667 | P13: 65682.092 | Q13: 0.58948692 | R13: 1.3333333 | S13: 50527.451 | T13: 47158.954 | U13: 0.21401744 | V13: WARNING
A14: 10 | B14: ='Price Projection'!B14 | C14: 2.6666667 | D14: 94317.908 | E14: 9431.7908 | F14: 103749.7 | G14: 0.64843562 | H14: 0 | I14: 0 | J14: 2.6666667 | K14: 103749.7 | L14: 2.6666667 | M14: 1.7291616 | N14: 0.93750503 | O14: 0.66666667 | P14: 56250.302 | Q14: 0.64843562 | R14: 1.3333333 | S14: 55580.196 | T14: 51874.849 | U14: 0.13541918 | V14: WARNING

Sheet Income Engine
A1: Income Engine — Borrow-Funded Income
A3: Year | B3: BTC Price | C3: Starting Collateral BTC | D3: Starting Debt | E3: Interest Accrued | F3: Debt After Interest | G3: Selected Income Draw | H3: Max Available Annual Income | I3: Income Borrowed | J3: Unfunded Income | K3: Cumulative Income Borrowed | L3: Ending Debt | M3: Debt BTC Equivalent | N3: Net BTC After Debt | O3: Net Equity USD | P3: Effective LTV End | Q3: Margin-Call Price | R3: Liquidation Price | S3: Drop to Liquidation | T3: Sustainability Status
A4: 0 | B4: ='Price Projection'!B4 | C4: 2 | D4: 0 | E4: 0 | F4: 0 | G4: 0 | H4: 42000 | I4: 0 | J4: 0 | K4: 0 | L4: 0 | M4: 0 | N4: 2 | O4: 120000 | P4: 0 | Q4: 0 | R4: 0 | S4: 0 | T4: SAFE
A5: 1 | B5: ='Price Projection'!B5 | C5: 2 | D5: 0 | E5: 0 | F5: 0 | G5: 50000 | H5: 42000 | I5: 42000 | J5: 8000 | K5: 42000 | L5: 42000 | M5: 0.7 | N5: 1.3 | O5: 78000 | P5: 0.35 | Q5: 30000 | R5: 28000 | S5: 0.53333333 | T5: CONSTRAINED
A6: 2 | B6: ='Price Projection'!B6 | C6: 2 | D6: 42000 | E6: 4200 | F6: 46200 | G6: 50000 | H6: 0 | I6: 0 | J6: 50000 | K6: 42000 | L6: 46200 | M6: 0.77 | N6: 1.23 | O6: 73800 | P6: 0.385 | Q6: 33000 | R6: 30800 | S6: 0.48666667 | T6: WARNING
A7: 3 | B7: ='Price Projection'!B7 | C7: 2 | D7: 46200 | E7: 4620 | F7: 50820 | G7: 50000 | H7: 0 | I7: 0 | J7: 50000 | K7: 42000 | L7: 50820 | M7: 0.847 | N7: 1.153 | O7: 69180 | P7: 0.4235 | Q7: 36300 | R7: 33880 | S7: 0.43533333 | T7: WARNING
A8: 4 | B8: ='Price Projection'!B8 | C8: 2 | D8: 50820 | E8: 5082 | F8: 55902 | G8: 50000 | H8: 0 | I8: 0 | J8: 50000 | K8: 42000 | L8: 55902 | M8: 0.9317 | N8: 1.0683 | O8: 64098 | P8: 0.46585 | Q8: 39930 | R8: 37268 | S8: 0.37886667 | T8: WARNING
A9: 5 | B9: ='Price Projection'!B9 | C9: 2 | D9: 55902 | E9: 5590.2 | F9: 61492.2 | G9: 50000 | H9: 0 | I9: 0 | J9: 50000 | K9: 42000 | L9: 61492.2 | M9: 1.02487 | N9: 0.97513 | O9: 58507.8 | P9: 0.512435 | Q9: 43923 | R9: 40994.8 | S9: 0.31675333 | T9: WARNING
A10: 6 | B10: ='Price Projection'!B10 | C10: 2 | D10: 61492.2 | E10: 6149.22 | F10: 67641.42 | G10: 50000 | H10: 0 | I10: 0 | J10: 50000 | K10: 42000 | L10: 67641.42 | M10: 1.127357 | N10: 0.872643 | O10: 52358.58 | P10: 0.5636785 | Q10: 48315.3 | R10: 45094.28 | S10: 0.24842867 | T10: WARNING
A11: 7 | B11: ='Price Projection'!B11 | C11: 2 | D11: 67641.42 | E11: 6764.142 | F11: 74405.562 | G11: 50000 | H11: 0 | I11: 0 | J11: 50000 | K11: 42000 | L11: 74405.562 | M11: 1.2400927 | N11: 0.7599073 | O11: 45594.438 | P11: 0.62004635 | Q11: 53146.83 | R11: 49603.708 | S11: 0.17327153 | T11: WARNING
A12: 8 | B12: ='Price Projection'!B12 | C12: 2 | D12: 74405.562 | E12: 7440.5562 | F12: 81846.118 | G12: 50000 | H12: 0 | I12: 0 | J12: 50000 | K12: 42000 | L12: 81846.118 | M12: 1.364102 | N12: 0.63589803 | O12: 38153.882 | P12: 0.68205099 | Q12: 58461.513 | R12: 54564.079 | S12: 0.090598687 | T12: WARNING
A13: 9 | B13: ='Price Projection'!B13 | C13: 2 | D13: 81846.118 | E13: 8184.6118 | F13: 90030.73 | G13: 50000 | H13: 0 | I13: 0 | J13: 50000 | K13: 42000 | L13: 90030.73 | M13: 1.5005122 | N13: 0.49948783 | O13: 29969.27 | P13: 0.75025608 | Q13: 64307.664 | R13: 60020.487 | S13: -0.00034144467 | T13: LIQUIDATED
A14: 10 | B14: ='Price Projection'!B14 | C14: 2 | D14: 90030.73 | E14: 9003.073 | F14: 99033.803 | G14: 50000 | H14: 0 | I14: 0 | J14: 50000 | K14: 42000 | L14: 99033.803 | M14: 1.6505634 | N14: 0.34943662 | O14: 20966.197 | P14: 0.82528169 | Q14: 70738.431 | R14: 66022.535 | S14: -0.10037559 | T14: LIQUIDATED

Sheet Risk Alerts
A1: Risk Alerts
A3: Metric | B3: Value
A4: Accumulation risk path
A5: Accumulation max effective LTV | B5: 0.64843562
A6: Accumulation min drop-to-liquidation | B6: 0.13541918
A7: Accumulation first non-safe year | B7: 5
A8: Accumulation liquidation year | B8: None
A9: Accumulation total interest accrued | B9: 63749.698
A10: Accumulation total new borrowing | B10: 40000
A11: Accumulation ending net BTC | B11: 0.93750503
A12: Accumulation BTC outperformance vs passive | B12: -1.062495
A13: Income risk path
A14: Income max effective LTV | B14: 0.82528169
A15: Income min drop-to-liquidation | B15: -0.10037559
A16: Income first constrained year | B16: 1
A17: Income liquidation year | B17: 9
A18: Income total interest accrued | B18: 57033.803
A19: Income total funded | B19: 42000
A20: Income total shortfall | B20: 458000
A21: Passive hold comparison
A22: Passive BTC held | B22: 2
A23: Passive ending value | B23: 120000

Sheet Summary
A1: BTC-Backed Loan Model v2 Summary
A3: Metric | B3: Value
A4: Passive starting BTC | B4: 2
A5: Passive ending BTC | B5: 2
A6: Passive ending value | B6: 120000
A7: Accumulation setup gross BTC | B7: 2.6666667
A8: Accumulation ending gross BTC | B8: 2.6666667
A9: Accumulation ending debt | B9: 103749.7
A10: Accumulation ending net BTC | B10: 0.93750503
A11: Accumulation ending LTV | B11: 0.64843562
A12: Accumulation status | B12: WARNING
A13: Income selected draw year 1 | B13: 50000
A14: Income funded year 1 | B14: 42000
A15: Income shortfall year 1 | B15: 8000
A16: Income ending debt | B16: 99033.803
A17: Income ending net BTC | B17: 0.34943662
A18: Income status | B18: LIQUIDATED

Sheet Audit Examples
A1: Audit Examples
A3: Audit Check | B3: Expected / Model Value
A4: Starting BTC | B4: 2
A5: Target effective LTV | B5: 0.25
A6: Final collateral BTC | B6: 2.6666667
A7: BTC purchased | B7: 0.66666667
A8: Debt | B8: 40000
A9: Effective LTV | B9: 0.25
A10: Liquidation price | B10: 20000
A13: Double-loop / 30.6% effective LTV example
A14: Starting BTC | B14: 2
A15: BTC price | B15: 60000
A16: Gross BTC ≈ | B16: 2.883
A17: Effective LTV ≈ | B17: 0.306
A18: Debt ≈ | B18: 53000
A20: Income capacity example
A21: Collateral BTC | B21: 2
A22: BTC price | B22: 100000
A23: Existing debt | B23: 30000
A24: Income LTV ceiling | B24: 0.35
A25: Selected income draw | B25: 50000
A26: Max safe debt | B26: 70000
A27: Income borrowed | B27: 40000
A28: Unfunded income | B28: 10000
A29: Debt end | B29: 70000
